yaqd_bronkhorst/VERSION
yaqd_bronkhorst/__init__.py
yaqd_bronkhorst/__version__.py
yaqd_bronkhorst/_bronkhorst_mfc_flow_bus.py
yaqd_bronkhorst/_bronkhorst_mfc_rs232.py
yaqd_bronkhorst/bronkhorst-mfc-flow-bus.avpr
yaqd_bronkhorst/bronkhorst-mfc-flow-bus.toml
yaqd_bronkhorst/bronkhorst-mfc-rs232.avpr
yaqd_bronkhorst/bronkhorst-mfc-rs232.toml
yaqd_bronkhorst-2023.8.0.dist-info/entry_points.txt
yaqd_bronkhorst-2023.8.0.dist-info/LICENSE
yaqd_bronkhorst-2023.8.0.dist-info/WHEEL
yaqd_bronkhorst-2023.8.0.dist-info/METADATA
yaqd_bronkhorst-2023.8.0.dist-info/RECORD
