Metadata-Version: 2.1
Name: yaqd-bronkhorst
Version: 2023.8.0
Summary: yaq daemons for Bronkhorst hardware.
Home-page: https://yaq.fyi
Author: yaq developers
Requires-Python: >=3.7
Classifier: Development Status :: 2 - Pre-Alpha
Classifier: Intended Audience :: Science/Research
Classifier: License :: OSI Approved :: GNU Lesser General Public License v3 (LGPLv3)
Classifier: Natural Language :: English
Classifier: Programming Language :: Python :: 3
Classifier: Programming Language :: Python :: 3.8
Classifier: Programming Language :: Python :: 3.9
Classifier: Programming Language :: Python :: 3.10
Classifier: Programming Language :: Python :: 3.11
Classifier: Topic :: Scientific/Engineering
Requires-Dist: yaqd-core>=2020.06.3
Requires-Dist: bronkhorst-propar
Requires-Dist: numpy
Requires-Dist: pySerial
Requires-Dist: black ; extra == "dev"
Requires-Dist: pre-commit ; extra == "dev"
Project-URL: Issues, https://github.com/yaq-project/yaqd-bronkhorst/issues
Project-URL: Source, https://github.com/yaq-project/yaqd-bronkhorst
Provides-Extra: dev
